LICENCE.txt
MANIFEST.in
README.rst
setup.py
cmsplugin_slideshows/__init__.py
cmsplugin_slideshows/cms_plugins.py
cmsplugin_slideshows/cms_toolbars.py
cmsplugin_slideshows/models.py
cmsplugin_slideshows.egg-info/PKG-INFO
cmsplugin_slideshows.egg-info/SOURCES.txt
cmsplugin_slideshows.egg-info/dependency_links.txt
cmsplugin_slideshows.egg-info/not-zip-safe
cmsplugin_slideshows.egg-info/requires.txt
cmsplugin_slideshows.egg-info/top_level.txt
cmsplugin_slideshows/migrations/0001_initial.py
cmsplugin_slideshows/migrations/__init__.py
cmsplugin_slideshows/templates/cmsplugin_slideshows/index.html