Metadata-Version: 1.1
Name: cmsplugin-slideshows
Version: 0.2.0
Summary: 
